{
    "system": "esy-reputation",
    "translations":
    {
        "GENERAL.error.playernotregistered":
        {
            "en_US": "&cThe target player is not registered.",
            "de_DE": "&cDieser Spieler ist nicht registriert."
        },
        "GENERAL.error.player.notset":
        {
            "en_US": "&cYou have to specify a player!",
            "de_DE": "&cDu musst einen Spieler angeben!"
        },
        "GENERAL.error.player.evaluate.self":
        {
            "en_US": "&cYou can't rate yourself!",
            "de_DE": "&cDu kannst dich nicht selbst bewerten!"
        },
        "GENERAL.success.evaluate":
        {
            "en_US": "&7You have rated &6[player] &7with &e[stars]",
            "de_DE": "&7Du hast &6[player] &7mit &e[stars] bewertet."
        },
        "GUI.evaluate.title":
        {
            "en_US": "Rating [player]",
            "de_DE": "Bewerte [player]"
        },
        "GUI.evaluate.item.stars":
        {
            "en_US": "Stars &x&F&F&D&8&0&0⭐",
            "de_DE": "Sterne &x&F&F&D&8&0&0⭐"
        },
        "GUI.evaluate.item.star":
        {
            "en_US": "Star &x&F&F&D&8&0&0⭐",
            "de_DE": "Stern &x&F&F&D&8&0&0⭐"
        },
        "GUI.evaluate.item.lore":
        {
            "en_US": "&8» <#F9BD31>Click to rate",
            "de_DE": "&8» <#F9BD31>Klicke zum Bewerten"
        }
    }
}
